README.md
setup.cfg
setup.py
pythreshold/__init__.py
pythreshold/main.py
pythreshold/utils.py
pythreshold.egg-info/PKG-INFO
pythreshold.egg-info/SOURCES.txt
pythreshold.egg-info/dependency_links.txt
pythreshold.egg-info/entry_points.txt
pythreshold.egg-info/requires.txt
pythreshold.egg-info/top_level.txt
pythreshold/global_th/__init__.py
pythreshold/global_th/min_err.py
pythreshold/global_th/otsu.py
pythreshold/global_th/p_tile.py
pythreshold/global_th/two_peaks.py
pythreshold/global_th/entropy/__init__.py
pythreshold/global_th/entropy/johannsen.py
pythreshold/global_th/entropy/kapur.py
pythreshold/global_th/entropy/pun.py
pythreshold/local_th/__init__.py
pythreshold/local_th/bernsen.py
pythreshold/local_th/bradley_roth.py
pythreshold/local_th/contrast.py
pythreshold/local_th/feng.py
pythreshold/local_th/lmean.py
pythreshold/local_th/niblack.py
pythreshold/local_th/nick.py
pythreshold/local_th/sauvola.py
pythreshold/local_th/singh.py
pythreshold/local_th/wolf.py