Metadata-Version: 2.1
Name: pythreshold
Version: 0.3.1
Summary: Numpy/Scipy implementations of state-of-the-art image thresholding algorithms
Home-page: https://github.com/manuelaguadomtz/pythreshold
Author: BSc. Manuel Aguado Martínez
Author-email: manuelaguadomtz@gmail.com
License: UNKNOWN
Keywords: thresholding entropy
Platform: UNKNOWN
Classifier: Intended Audience :: Science/Research
Classifier: Operating System :: OS Independent
Classifier: Topic :: Scientific/Engineering
Classifier: Programming Language :: Python
Classifier: License :: OSI Approved :: MIT License
